ros2_unbag/__init__.py
ros2_unbag/export.py
ros2_unbag/core/__init__.py
ros2_unbag/core/bag_reader.py
ros2_unbag/core/bag_writer.py
ros2_unbag/core/exporter.py
ros2_unbag/core/processors/__init__.py
ros2_unbag/core/processors/base.py
ros2_unbag/core/processors/image.py
ros2_unbag/core/processors/pointcloud.py
ros2_unbag/core/routines/__init__.py
ros2_unbag/core/routines/base.py
ros2_unbag/core/routines/default.py
ros2_unbag/core/routines/image.py
ros2_unbag/core/routines/pointcloud.py
ros2_unbag/core/routines/video.py
ros2_unbag/core/utils/__init__.py
ros2_unbag/core/utils/file_utils.py
ros2_unbag/core/utils/image_utils.py
ros2_unbag/core/utils/pointcloud_utils.py
ros2_unbag/core/utils/video_utils.py
ros2_unbag/ui/__init__.py
ros2_unbag/ui/main_window.py
ros2_unbag/ui/styles.py
ros2_unbag/ui/assets/__init__.py
ros2_unbag/ui/assets/badge.svg
ros2_unbag/ui/assets/loading.gif
ros2_unbag/ui/assets/title.png
ros2_unbag/ui/widgets/__init__.py
ros2_unbag/ui/widgets/global_settings.py
ros2_unbag/ui/widgets/processor_chain.py
ros2_unbag/ui/widgets/topic_list.py
ros2_unbag/ui/widgets/topic_settings.py
ros2_unbag-1.2.0.dist-info/licenses/LICENSE
ros2_unbag-1.2.0.dist-info/licenses/LICENSE-3rdparty
ros2_unbag-1.2.0.dist-info/METADATA
ros2_unbag-1.2.0.dist-info/WHEEL
ros2_unbag-1.2.0.dist-info/entry_points.txt
ros2_unbag-1.2.0.dist-info/top_level.txt
ros2_unbag-1.2.0.dist-info/RECORD
