Metadata-Version: 2.4
Name: ros2_unbag
Version: 1.2.0
Summary: A ROS 2 tool for exporting bags to human readable files. Supports pluggable export routines to handle any message type.
Author-email: Lukas Ostendorf <lukas.ostendorf@ika.rwth-aachen.de>
Maintainer-email: Lukas Ostendorf <lukas.ostendorf@ika.rwth-aachen.de>
License: MIT License
Project-URL: homepage, https://github.com/ika-rwth-aachen/ros2_unbag
Keywords: ros2,rosbag,robotics,perception,ros2-export
Requires-Python: >=3.8
License-File: LICENSE
License-File: LICENSE-3rdparty
Requires-Dist: numpy==1.26.4
Requires-Dist: opencv-python-headless==4.11.0.86
Requires-Dist: pypcd4==1.3.0
Requires-Dist: PySide6==6.9.1
Requires-Dist: pyyaml==6.0.2
Requires-Dist: tqdm==4.67.1
Provides-Extra: test
Requires-Dist: pytest>=7.0; extra == "test"
Requires-Dist: pytest-cov>=4.0; extra == "test"
Dynamic: license-file
